{
   "abstract" : "apparently run a function in a higher stack frame",
   "author" : [
      "Michael Schwern <mschwern@cpan.org>",
      "David Golden <dagolden@cpan.org>"
   ],
   "dynamic_config" : 0,
   "generated_by" : "Dist::Zilla version 6.009, CPAN::Meta::Converter version 2.150010",
   "license" : [
      "perl_5"
   ],
   "meta-spec" : {
      "url" : "http://search.cpan.org/perldoc?CPAN::Meta::Spec",
      "version" : 2
   },
   "name" : "Sub-Uplevel",
   "no_index" : {
      "directory" : [
         "corpus",
         "examples",
         "t",
         "xt"
      ],
      "package" : [
         "DB"
      ]
   },
   "prereqs" : {
      "build" : {
         "requires" : {
            "ExtUtils::MakeMaker" : "0"
         }
      },
      "configure" : {
         "requires" : {
            "ExtUtils::MakeMaker" : "6.17",
            "perl" : "5.006"
         }
      },
      "runtime" : {
         "requires" : {
            "Carp" : "0",
            "Exporter" : "0",
            "ExtUtils::MakeMaker" : "0",
            "File::Spec" : "0",
            "Test::More" : "0",
            "constant" : "0",
            "lib" : "0",
            "perl" : "5.006",
            "strict" : "0",
            "warnings" : "0"
         }
      }
   },
   "provides" : {
      "Sub::Uplevel" : {
         "file" : "lib/Sub/Uplevel.pm",
         "version" : "0.2800"
      }
   },
   "release_status" : "stable",
   "resources" : {
      "bugtracker" : {
         "web" : "https://github.com/Perl-Toolchain-Gang/Sub-Uplevel/issues"
      },
      "homepage" : "https://github.com/Perl-Toolchain-Gang/Sub-Uplevel",
      "repository" : {
         "url" : "https://github.com/Perl-Toolchain-Gang/Sub-Uplevel.git"
      }
   },
   "version" : "0.2800",
   "x_authority" : "cpan:DAGOLDEN",
   "x_contributors" : [
      "Adam Kennedy <adamk@cpan.org>",
      "Alexandr Ciornii <alexchorny@gmail.com>",
      "David Golden <xdg@xdg.me>",
      "Graham Ollis <plicease@cpan.org>",
      "J. Nick Koston <nick@cpanel.net>",
      "Michael Gray <mg13@sanger.ac.uk>"
   ],
   "x_serialization_backend" : "JSON::PP version 4.06"
}
